{
  "type": "Feature",
  "properties": {
    "gn:admin1_code":"0.0",
    "gn:asciiname":"Sucker Garden",
    "gn:country_code":"SX",
    "gn:dem":86,
    "gn:feature_class":"P",
    "gn:feature_code":"PPLL",
    "gn:name":"Sucker Garden",
    "gn:population":0,
    "gn:timezone":"America/Lower_Princes",
    "iso:country":"SX",
    "wof:name":"Sucker Garden",
    "wof:placetype":"locality"
},
  "geometry": {"coordinates":[-63.03486,18.04084],"type":"Point"}
}