{
  "type": "Feature",
  "properties": {
    "gn:admin1_code":"0.0",
    "gn:asciiname":"Koolbaai",
    "gn:country_code":"SX",
    "gn:dem":16,
    "gn:feature_class":"P",
    "gn:feature_code":"PPL",
    "gn:name":"Koolbaai",
    "gn:population":6000,
    "gn:timezone":"America/Lower_Princes",
    "iso:country":"SX",
    "name:nld_x_preferred":[
        "Koolbaai"
    ],
    "name:und_x_variant":[
        "Cole Bay"
    ],
    "wof:name":"Koolbaai",
    "wof:placetype":"locality",
    "wof:population":6000
},
  "geometry": {"coordinates":[-63.08397,18.04048],"type":"Point"}
}