{
  "type": "Feature",
  "properties": {
    "gn:admin1_code":"0.0",
    "gn:asciiname":"Beacon Hill",
    "gn:country_code":"SX",
    "gn:dem":4,
    "gn:feature_class":"P",
    "gn:feature_code":"PPLL",
    "gn:name":"Beacon Hill",
    "gn:population":0,
    "gn:timezone":"America/Lower_Princes",
    "iso:country":"SX",
    "name:ceb_x_preferred":[
        "Beacon Hill"
    ],
    "name:deu_x_preferred":[
        "Beacon Hill"
    ],
    "name:fra_x_preferred":[
        "Beacon Hill"
    ],
    "name:ita_x_preferred":[
        "Beacon Hill"
    ],
    "name:kor_x_preferred":[
        "\ube44\ucee8\ud790"
    ],
    "name:rus_x_preferred":[
        "\u0411\u0438\u043a\u043e\u043d-\u0425\u0438\u043b\u043b"
    ],
    "name:swe_x_preferred":[
        "Beacon Hill"
    ],
    "wof:name":"Beacon Hill",
    "wof:placetype":"locality"
},
  "geometry": {"coordinates":[-63.11594,18.0376],"type":"Point"}
}