{
  "type": "Feature",
  "properties": {
    "gn:admin1_code":"0.0",
    "gn:asciiname":"Beacon Hill",
    "gn:country_code":"SX",
    "gn:dem":4,
    "gn:feature_class":"P",
    "gn:feature_code":"PPLL",
    "gn:name":"Beacon Hill",
    "gn:population":0,
    "gn:timezone":"America/Lower_Princes",
    "iso:country":"SX",
    "wof:name":"Beacon Hill",
    "wof:placetype":"locality"
},
  "geometry": {"coordinates":[-63.11594,18.0376],"type":"Point"}
}