{
  "type": "Feature",
  "properties": {
    "gn:admin1_code":"0.0",
    "gn:asciiname":"Tamarind Hill",
    "gn:country_code":"SX",
    "gn:dem":70,
    "gn:feature_class":"P",
    "gn:feature_code":"PPLL",
    "gn:name":"Tamarind Hill",
    "gn:population":0,
    "gn:timezone":"America/Lower_Princes",
    "iso:country":"SX",
    "wof:name":"Tamarind Hill",
    "wof:placetype":"locality"
},
  "geometry": {"coordinates":[-63.02332,18.04303],"type":"Point"}
}