{
  "type": "Feature",
  "properties": {
    "gn:country":"SX",
    "gn:fcode":"PPLL",
    "gn:population":8467,
    "iso:country":"SX",
    "name:eng_x_preferred":[
        "Cul de Sac"
    ],
    "name:fra_x_preferred":[
        "Cul de Sac"
    ],
    "name:nld_x_preferred":[
        "Cul de Sac"
    ],
    "name:pol_x_preferred":[
        "Cul de Sac"
    ],
    "name:und_x_variant":[
        "Duth Cul de Sac"
    ],
    "qs_pg:aaroncc":"SX",
    "qs_pg:gn_country":"SX",
    "qs_pg:gn_fcode":"PPLL",
    "qs_pg:gn_pop":8467,
    "qs_pg:name":"Cul de Sac",
    "qs_pg:photos_9r":0,
    "qs_pg:photos_sr":0,
    "qs_pg:pop_sr":5,
    "qs_pg:qs_pg_placetype":"locality",
    "wof:name":"Cul de Sac",
    "wof:placetype":"locality",
    "wof:population":8467
},
  "geometry": {"coordinates":[-63.06542,18.03868],"type":"Point"}
}