{
  "type": "Feature",
  "properties": {
    "gn:admin1_code":"0.0",
    "gn:asciiname":"Experiment",
    "gn:country_code":"SX",
    "gn:dem":11,
    "gn:feature_class":"P",
    "gn:feature_code":"PPLL",
    "gn:name":"Experiment",
    "gn:population":0,
    "gn:timezone":"America/Lower_Princes",
    "iso:country":"SX",
    "wof:name":"Experiment",
    "wof:placetype":"locality"
},
  "geometry": {"coordinates":[-63.03586,18.02834],"type":"Point"}
}