{
  "type": "Feature",
  "properties": {
    "gn:admin1_code":"0.0",
    "gn:asciiname":"Claude Estate",
    "gn:country_code":"SX",
    "gn:dem":65,
    "gn:feature_class":"P",
    "gn:feature_code":"PPLL",
    "gn:name":"Claude Estate",
    "gn:population":0,
    "gn:timezone":"America/Lower_Princes",
    "iso:country":"SX",
    "wof:name":"Claude Estate",
    "wof:placetype":"locality"
},
  "geometry": {"coordinates":[-63.05141999999999,18.04243],"type":"Point"}
}